
{"order":100,"items":[{"name":"Monai.Deploy.InformaticsGateway.Api","href":"Monai.Deploy.InformaticsGateway.Api.html","topicHref":"Monai.Deploy.InformaticsGateway.Api.html","topicUid":"Monai.Deploy.InformaticsGateway.Api","type":"Namespace","items":[{"name":"DataKeyValuePair","href":"Monai.Deploy.InformaticsGateway.Api.DataKeyValuePair.html","topicHref":"Monai.Deploy.InformaticsGateway.Api.DataKeyValuePair.html","topicUid":"Monai.Deploy.InformaticsGateway.Api.DataKeyValuePair","type":"Class"},{"name":"DataLinkType","href":"Monai.Deploy.InformaticsGateway.Api.DataLinkType.html","topicHref":"Monai.Deploy.InformaticsGateway.Api.DataLinkType.html","topicUid":"Monai.Deploy.InformaticsGateway.Api.DataLinkType","type":"Enum"},{"name":"EditMode","href":"Monai.Deploy.InformaticsGateway.Api.EditMode.html","topicHref":"Monai.Deploy.InformaticsGateway.Api.EditMode.html","topicUid":"Monai.Deploy.InformaticsGateway.Api.EditMode","type":"Enum"},{"name":"Hl7ApplicationConfigEntity","href":"Monai.Deploy.InformaticsGateway.Api.Hl7ApplicationConfigEntity.html","topicHref":"Monai.Deploy.InformaticsGateway.Api.Hl7ApplicationConfigEntity.html","topicUid":"Monai.Deploy.InformaticsGateway.Api.Hl7ApplicationConfigEntity","type":"Class"},{"name":"IKeyValuePair<TKey, TValue>","href":"Monai.Deploy.InformaticsGateway.Api.IKeyValuePair-2.html","topicHref":"Monai.Deploy.InformaticsGateway.Api.IKeyValuePair-2.html","topicUid":"Monai.Deploy.InformaticsGateway.Api.IKeyValuePair`2","type":"Interface"},{"name":"LoggingDataDictionary<TKey, TValue>","href":"Monai.Deploy.InformaticsGateway.Api.LoggingDataDictionary-2.html","topicHref":"Monai.Deploy.InformaticsGateway.Api.LoggingDataDictionary-2.html","topicUid":"Monai.Deploy.InformaticsGateway.Api.LoggingDataDictionary`2","type":"Class"},{"name":"SourceApplicationEntity","href":"Monai.Deploy.InformaticsGateway.Api.SourceApplicationEntity.html","topicHref":"Monai.Deploy.InformaticsGateway.Api.SourceApplicationEntity.html","topicUid":"Monai.Deploy.InformaticsGateway.Api.SourceApplicationEntity","type":"Class"},{"name":"StringKeyValuePair","href":"Monai.Deploy.InformaticsGateway.Api.StringKeyValuePair.html","topicHref":"Monai.Deploy.InformaticsGateway.Api.StringKeyValuePair.html","topicUid":"Monai.Deploy.InformaticsGateway.Api.StringKeyValuePair","type":"Class"},{"name":"VirtualApplicationEntity","href":"Monai.Deploy.InformaticsGateway.Api.VirtualApplicationEntity.html","topicHref":"Monai.Deploy.InformaticsGateway.Api.VirtualApplicationEntity.html","topicUid":"Monai.Deploy.InformaticsGateway.Api.VirtualApplicationEntity","type":"Class"}]},{"name":"Monai.Deploy.InformaticsGateway.Api.Mllp","href":"Monai.Deploy.InformaticsGateway.Api.Mllp.html","topicHref":"Monai.Deploy.InformaticsGateway.Api.Mllp.html","topicUid":"Monai.Deploy.InformaticsGateway.Api.Mllp","type":"Namespace","items":[{"name":"IMllpClient","href":"Monai.Deploy.InformaticsGateway.Api.Mllp.IMllpClient.html","topicHref":"Monai.Deploy.InformaticsGateway.Api.Mllp.IMllpClient.html","topicUid":"Monai.Deploy.InformaticsGateway.Api.Mllp.IMllpClient","type":"Interface"},{"name":"IMllpExtract","href":"Monai.Deploy.InformaticsGateway.Api.Mllp.IMllpExtract.html","topicHref":"Monai.Deploy.InformaticsGateway.Api.Mllp.IMllpExtract.html","topicUid":"Monai.Deploy.InformaticsGateway.Api.Mllp.IMllpExtract","type":"Interface"},{"name":"IMllpService","href":"Monai.Deploy.InformaticsGateway.Api.Mllp.IMllpService.html","topicHref":"Monai.Deploy.InformaticsGateway.Api.Mllp.IMllpService.html","topicUid":"Monai.Deploy.InformaticsGateway.Api.Mllp.IMllpService","type":"Interface"},{"name":"MllpClientResult","href":"Monai.Deploy.InformaticsGateway.Api.Mllp.MllpClientResult.html","topicHref":"Monai.Deploy.InformaticsGateway.Api.Mllp.MllpClientResult.html","topicUid":"Monai.Deploy.InformaticsGateway.Api.Mllp.MllpClientResult","type":"Class"}]},{"name":"Monai.Deploy.InformaticsGateway.Api.Models","href":"Monai.Deploy.InformaticsGateway.Api.Models.html","topicHref":"Monai.Deploy.InformaticsGateway.Api.Models.html","topicUid":"Monai.Deploy.InformaticsGateway.Api.Models","type":"Namespace","items":[{"name":"BaseApplicationEntity","href":"Monai.Deploy.InformaticsGateway.Api.Models.BaseApplicationEntity.html","topicHref":"Monai.Deploy.InformaticsGateway.Api.Models.BaseApplicationEntity.html","topicUid":"Monai.Deploy.InformaticsGateway.Api.Models.BaseApplicationEntity","type":"Class"},{"name":"DestinationApplicationEntity","href":"Monai.Deploy.InformaticsGateway.Api.Models.DestinationApplicationEntity.html","topicHref":"Monai.Deploy.InformaticsGateway.Api.Models.DestinationApplicationEntity.html","topicUid":"Monai.Deploy.InformaticsGateway.Api.Models.DestinationApplicationEntity","type":"Class"},{"name":"DicomAssociationInfo","href":"Monai.Deploy.InformaticsGateway.Api.Models.DicomAssociationInfo.html","topicHref":"Monai.Deploy.InformaticsGateway.Api.Models.DicomAssociationInfo.html","topicUid":"Monai.Deploy.InformaticsGateway.Api.Models.DicomAssociationInfo","type":"Class"},{"name":"ExportRequestDataMessage","href":"Monai.Deploy.InformaticsGateway.Api.Models.ExportRequestDataMessage.html","topicHref":"Monai.Deploy.InformaticsGateway.Api.Models.ExportRequestDataMessage.html","topicUid":"Monai.Deploy.InformaticsGateway.Api.Models.ExportRequestDataMessage","type":"Class"},{"name":"ExternalAppDetails","href":"Monai.Deploy.InformaticsGateway.Api.Models.ExternalAppDetails.html","topicHref":"Monai.Deploy.InformaticsGateway.Api.Models.ExternalAppDetails.html","topicUid":"Monai.Deploy.InformaticsGateway.Api.Models.ExternalAppDetails","type":"Class"},{"name":"HL7DestinationEntity","href":"Monai.Deploy.InformaticsGateway.Api.Models.HL7DestinationEntity.html","topicHref":"Monai.Deploy.InformaticsGateway.Api.Models.HL7DestinationEntity.html","topicUid":"Monai.Deploy.InformaticsGateway.Api.Models.HL7DestinationEntity","type":"Class"},{"name":"MonaiApplicationEntity","href":"Monai.Deploy.InformaticsGateway.Api.Models.MonaiApplicationEntity.html","topicHref":"Monai.Deploy.InformaticsGateway.Api.Models.MonaiApplicationEntity.html","topicUid":"Monai.Deploy.InformaticsGateway.Api.Models.MonaiApplicationEntity","type":"Class"}]},{"name":"Monai.Deploy.InformaticsGateway.Api.PlugIns","href":"Monai.Deploy.InformaticsGateway.Api.PlugIns.html","topicHref":"Monai.Deploy.InformaticsGateway.Api.PlugIns.html","topicUid":"Monai.Deploy.InformaticsGateway.Api.PlugIns","type":"Namespace","items":[{"name":"IInputDataPlugIn","href":"Monai.Deploy.InformaticsGateway.Api.PlugIns.IInputDataPlugIn.html","topicHref":"Monai.Deploy.InformaticsGateway.Api.PlugIns.IInputDataPlugIn.html","topicUid":"Monai.Deploy.InformaticsGateway.Api.PlugIns.IInputDataPlugIn","type":"Interface"},{"name":"IInputDataPlugInEngine","href":"Monai.Deploy.InformaticsGateway.Api.PlugIns.IInputDataPlugInEngine.html","topicHref":"Monai.Deploy.InformaticsGateway.Api.PlugIns.IInputDataPlugInEngine.html","topicUid":"Monai.Deploy.InformaticsGateway.Api.PlugIns.IInputDataPlugInEngine","type":"Interface"},{"name":"IInputHL7DataPlugIn","href":"Monai.Deploy.InformaticsGateway.Api.PlugIns.IInputHL7DataPlugIn.html","topicHref":"Monai.Deploy.InformaticsGateway.Api.PlugIns.IInputHL7DataPlugIn.html","topicUid":"Monai.Deploy.InformaticsGateway.Api.PlugIns.IInputHL7DataPlugIn","type":"Interface"},{"name":"IInputHL7DataPlugInEngine","href":"Monai.Deploy.InformaticsGateway.Api.PlugIns.IInputHL7DataPlugInEngine.html","topicHref":"Monai.Deploy.InformaticsGateway.Api.PlugIns.IInputHL7DataPlugInEngine.html","topicUid":"Monai.Deploy.InformaticsGateway.Api.PlugIns.IInputHL7DataPlugInEngine","type":"Interface"},{"name":"IOutputDataPlugIn","href":"Monai.Deploy.InformaticsGateway.Api.PlugIns.IOutputDataPlugIn.html","topicHref":"Monai.Deploy.InformaticsGateway.Api.PlugIns.IOutputDataPlugIn.html","topicUid":"Monai.Deploy.InformaticsGateway.Api.PlugIns.IOutputDataPlugIn","type":"Interface"},{"name":"IOutputDataPlugInEngine","href":"Monai.Deploy.InformaticsGateway.Api.PlugIns.IOutputDataPlugInEngine.html","topicHref":"Monai.Deploy.InformaticsGateway.Api.PlugIns.IOutputDataPlugInEngine.html","topicUid":"Monai.Deploy.InformaticsGateway.Api.PlugIns.IOutputDataPlugInEngine","type":"Interface"},{"name":"PlugInNameAttribute","href":"Monai.Deploy.InformaticsGateway.Api.PlugIns.PlugInNameAttribute.html","topicHref":"Monai.Deploy.InformaticsGateway.Api.PlugIns.PlugInNameAttribute.html","topicUid":"Monai.Deploy.InformaticsGateway.Api.PlugIns.PlugInNameAttribute","type":"Class"},{"name":"SR","href":"Monai.Deploy.InformaticsGateway.Api.PlugIns.SR.html","topicHref":"Monai.Deploy.InformaticsGateway.Api.PlugIns.SR.html","topicUid":"Monai.Deploy.InformaticsGateway.Api.PlugIns.SR","type":"Class"}]},{"name":"Monai.Deploy.InformaticsGateway.Api.Rest","href":"Monai.Deploy.InformaticsGateway.Api.Rest.html","topicHref":"Monai.Deploy.InformaticsGateway.Api.Rest.html","topicUid":"Monai.Deploy.InformaticsGateway.Api.Rest","type":"Namespace","items":[{"name":"ConnectionAuthType","href":"Monai.Deploy.InformaticsGateway.Api.Rest.ConnectionAuthType.html","topicHref":"Monai.Deploy.InformaticsGateway.Api.Rest.ConnectionAuthType.html","topicUid":"Monai.Deploy.InformaticsGateway.Api.Rest.ConnectionAuthType","type":"Enum"},{"name":"DicomWebConnectionDetails","href":"Monai.Deploy.InformaticsGateway.Api.Rest.DicomWebConnectionDetails.html","topicHref":"Monai.Deploy.InformaticsGateway.Api.Rest.DicomWebConnectionDetails.html","topicUid":"Monai.Deploy.InformaticsGateway.Api.Rest.DicomWebConnectionDetails","type":"Class"},{"name":"FhirResource","href":"Monai.Deploy.InformaticsGateway.Api.Rest.FhirResource.html","topicHref":"Monai.Deploy.InformaticsGateway.Api.Rest.FhirResource.html","topicUid":"Monai.Deploy.InformaticsGateway.Api.Rest.FhirResource","type":"Class"},{"name":"FhirStorageFormat","href":"Monai.Deploy.InformaticsGateway.Api.Rest.FhirStorageFormat.html","topicHref":"Monai.Deploy.InformaticsGateway.Api.Rest.FhirStorageFormat.html","topicUid":"Monai.Deploy.InformaticsGateway.Api.Rest.FhirStorageFormat","type":"Enum"},{"name":"FhirVersion","href":"Monai.Deploy.InformaticsGateway.Api.Rest.FhirVersion.html","topicHref":"Monai.Deploy.InformaticsGateway.Api.Rest.FhirVersion.html","topicUid":"Monai.Deploy.InformaticsGateway.Api.Rest.FhirVersion","type":"Enum"},{"name":"FileMetadataKeys","href":"Monai.Deploy.InformaticsGateway.Api.Rest.FileMetadataKeys.html","topicHref":"Monai.Deploy.InformaticsGateway.Api.Rest.FileMetadataKeys.html","topicUid":"Monai.Deploy.InformaticsGateway.Api.Rest.FileMetadataKeys","type":"Class"},{"name":"HealthStatusResponse","href":"Monai.Deploy.InformaticsGateway.Api.Rest.HealthStatusResponse.html","topicHref":"Monai.Deploy.InformaticsGateway.Api.Rest.HealthStatusResponse.html","topicUid":"Monai.Deploy.InformaticsGateway.Api.Rest.HealthStatusResponse","type":"Class"},{"name":"InferenceRequest","href":"Monai.Deploy.InformaticsGateway.Api.Rest.InferenceRequest.html","topicHref":"Monai.Deploy.InformaticsGateway.Api.Rest.InferenceRequest.html","topicUid":"Monai.Deploy.InformaticsGateway.Api.Rest.InferenceRequest","type":"Class"},{"name":"InferenceRequestDetails","href":"Monai.Deploy.InformaticsGateway.Api.Rest.InferenceRequestDetails.html","topicHref":"Monai.Deploy.InformaticsGateway.Api.Rest.InferenceRequestDetails.html","topicUid":"Monai.Deploy.InformaticsGateway.Api.Rest.InferenceRequestDetails","type":"Class"},{"name":"InferenceRequestException","href":"Monai.Deploy.InformaticsGateway.Api.Rest.InferenceRequestException.html","topicHref":"Monai.Deploy.InformaticsGateway.Api.Rest.InferenceRequestException.html","topicUid":"Monai.Deploy.InformaticsGateway.Api.Rest.InferenceRequestException","type":"Class"},{"name":"InferenceRequestMetadata","href":"Monai.Deploy.InformaticsGateway.Api.Rest.InferenceRequestMetadata.html","topicHref":"Monai.Deploy.InformaticsGateway.Api.Rest.InferenceRequestMetadata.html","topicUid":"Monai.Deploy.InformaticsGateway.Api.Rest.InferenceRequestMetadata","type":"Class"},{"name":"InferenceRequestResponse","href":"Monai.Deploy.InformaticsGateway.Api.Rest.InferenceRequestResponse.html","topicHref":"Monai.Deploy.InformaticsGateway.Api.Rest.InferenceRequestResponse.html","topicUid":"Monai.Deploy.InformaticsGateway.Api.Rest.InferenceRequestResponse","type":"Class"},{"name":"InferenceRequestState","href":"Monai.Deploy.InformaticsGateway.Api.Rest.InferenceRequestState.html","topicHref":"Monai.Deploy.InformaticsGateway.Api.Rest.InferenceRequestState.html","topicUid":"Monai.Deploy.InformaticsGateway.Api.Rest.InferenceRequestState","type":"Enum"},{"name":"InferenceRequestStatus","href":"Monai.Deploy.InformaticsGateway.Api.Rest.InferenceRequestStatus.html","topicHref":"Monai.Deploy.InformaticsGateway.Api.Rest.InferenceRequestStatus.html","topicUid":"Monai.Deploy.InformaticsGateway.Api.Rest.InferenceRequestStatus","type":"Enum"},{"name":"InferenceRequestType","href":"Monai.Deploy.InformaticsGateway.Api.Rest.InferenceRequestType.html","topicHref":"Monai.Deploy.InformaticsGateway.Api.Rest.InferenceRequestType.html","topicUid":"Monai.Deploy.InformaticsGateway.Api.Rest.InferenceRequestType","type":"Enum"},{"name":"InferenceStatusResponse","href":"Monai.Deploy.InformaticsGateway.Api.Rest.InferenceStatusResponse.html","topicHref":"Monai.Deploy.InformaticsGateway.Api.Rest.InferenceStatusResponse.html","topicUid":"Monai.Deploy.InformaticsGateway.Api.Rest.InferenceStatusResponse","type":"Class"},{"name":"InputConnectionDetails","href":"Monai.Deploy.InformaticsGateway.Api.Rest.InputConnectionDetails.html","topicHref":"Monai.Deploy.InformaticsGateway.Api.Rest.InputConnectionDetails.html","topicUid":"Monai.Deploy.InformaticsGateway.Api.Rest.InputConnectionDetails","type":"Class"},{"name":"InputInterfaceOperations","href":"Monai.Deploy.InformaticsGateway.Api.Rest.InputInterfaceOperations.html","topicHref":"Monai.Deploy.InformaticsGateway.Api.Rest.InputInterfaceOperations.html","topicUid":"Monai.Deploy.InformaticsGateway.Api.Rest.InputInterfaceOperations","type":"Enum"},{"name":"InputInterfaceType","href":"Monai.Deploy.InformaticsGateway.Api.Rest.InputInterfaceType.html","topicHref":"Monai.Deploy.InformaticsGateway.Api.Rest.InputInterfaceType.html","topicUid":"Monai.Deploy.InformaticsGateway.Api.Rest.InputInterfaceType","type":"Enum"},{"name":"RequestInputDataResource","href":"Monai.Deploy.InformaticsGateway.Api.Rest.RequestInputDataResource.html","topicHref":"Monai.Deploy.InformaticsGateway.Api.Rest.RequestInputDataResource.html","topicUid":"Monai.Deploy.InformaticsGateway.Api.Rest.RequestInputDataResource","type":"Class"},{"name":"RequestOutputDataResource","href":"Monai.Deploy.InformaticsGateway.Api.Rest.RequestOutputDataResource.html","topicHref":"Monai.Deploy.InformaticsGateway.Api.Rest.RequestOutputDataResource.html","topicUid":"Monai.Deploy.InformaticsGateway.Api.Rest.RequestOutputDataResource","type":"Class"},{"name":"RequestedInstance","href":"Monai.Deploy.InformaticsGateway.Api.Rest.RequestedInstance.html","topicHref":"Monai.Deploy.InformaticsGateway.Api.Rest.RequestedInstance.html","topicUid":"Monai.Deploy.InformaticsGateway.Api.Rest.RequestedInstance","type":"Class"},{"name":"RequestedSeries","href":"Monai.Deploy.InformaticsGateway.Api.Rest.RequestedSeries.html","topicHref":"Monai.Deploy.InformaticsGateway.Api.Rest.RequestedSeries.html","topicUid":"Monai.Deploy.InformaticsGateway.Api.Rest.RequestedSeries","type":"Class"},{"name":"RequestedStudy","href":"Monai.Deploy.InformaticsGateway.Api.Rest.RequestedStudy.html","topicHref":"Monai.Deploy.InformaticsGateway.Api.Rest.RequestedStudy.html","topicUid":"Monai.Deploy.InformaticsGateway.Api.Rest.RequestedStudy","type":"Class"},{"name":"ServiceStatus","href":"Monai.Deploy.InformaticsGateway.Api.Rest.ServiceStatus.html","topicHref":"Monai.Deploy.InformaticsGateway.Api.Rest.ServiceStatus.html","topicUid":"Monai.Deploy.InformaticsGateway.Api.Rest.ServiceStatus","type":"Enum"}]},{"name":"Monai.Deploy.InformaticsGateway.Api.Storage","href":"Monai.Deploy.InformaticsGateway.Api.Storage.html","topicHref":"Monai.Deploy.InformaticsGateway.Api.Storage.html","topicUid":"Monai.Deploy.InformaticsGateway.Api.Storage","type":"Namespace","items":[{"name":"DicomFileStorageMetadata","href":"Monai.Deploy.InformaticsGateway.Api.Storage.DicomFileStorageMetadata.html","topicHref":"Monai.Deploy.InformaticsGateway.Api.Storage.DicomFileStorageMetadata.html","topicUid":"Monai.Deploy.InformaticsGateway.Api.Storage.DicomFileStorageMetadata","type":"Class"},{"name":"FhirFileStorageMetadata","href":"Monai.Deploy.InformaticsGateway.Api.Storage.FhirFileStorageMetadata.html","topicHref":"Monai.Deploy.InformaticsGateway.Api.Storage.FhirFileStorageMetadata.html","topicUid":"Monai.Deploy.InformaticsGateway.Api.Storage.FhirFileStorageMetadata","type":"Class"},{"name":"FileStorageMetadata","href":"Monai.Deploy.InformaticsGateway.Api.Storage.FileStorageMetadata.html","topicHref":"Monai.Deploy.InformaticsGateway.Api.Storage.FileStorageMetadata.html","topicUid":"Monai.Deploy.InformaticsGateway.Api.Storage.FileStorageMetadata","type":"Class"},{"name":"Hl7FileStorageMetadata","href":"Monai.Deploy.InformaticsGateway.Api.Storage.Hl7FileStorageMetadata.html","topicHref":"Monai.Deploy.InformaticsGateway.Api.Storage.Hl7FileStorageMetadata.html","topicUid":"Monai.Deploy.InformaticsGateway.Api.Storage.Hl7FileStorageMetadata","type":"Class"},{"name":"MongoDBEntityBase","href":"Monai.Deploy.InformaticsGateway.Api.Storage.MongoDBEntityBase.html","topicHref":"Monai.Deploy.InformaticsGateway.Api.Storage.MongoDBEntityBase.html","topicUid":"Monai.Deploy.InformaticsGateway.Api.Storage.MongoDBEntityBase","type":"Class"},{"name":"Payload","href":"Monai.Deploy.InformaticsGateway.Api.Storage.Payload.html","topicHref":"Monai.Deploy.InformaticsGateway.Api.Storage.Payload.html","topicUid":"Monai.Deploy.InformaticsGateway.Api.Storage.Payload","type":"Class"},{"name":"Payload.PayloadState","href":"Monai.Deploy.InformaticsGateway.Api.Storage.Payload.PayloadState.html","topicHref":"Monai.Deploy.InformaticsGateway.Api.Storage.Payload.PayloadState.html","topicUid":"Monai.Deploy.InformaticsGateway.Api.Storage.Payload.PayloadState","type":"Enum"},{"name":"StorageObjectMetadata","href":"Monai.Deploy.InformaticsGateway.Api.Storage.StorageObjectMetadata.html","topicHref":"Monai.Deploy.InformaticsGateway.Api.Storage.StorageObjectMetadata.html","topicUid":"Monai.Deploy.InformaticsGateway.Api.Storage.StorageObjectMetadata","type":"Class"}]},{"name":"Monai.Deploy.InformaticsGateway.Client","href":"Monai.Deploy.InformaticsGateway.Client.html","topicHref":"Monai.Deploy.InformaticsGateway.Client.html","topicUid":"Monai.Deploy.InformaticsGateway.Client","type":"Namespace","items":[{"name":"Configuration","href":"Monai.Deploy.InformaticsGateway.Client.Configuration.html","topicHref":"Monai.Deploy.InformaticsGateway.Client.Configuration.html","topicUid":"Monai.Deploy.InformaticsGateway.Client.Configuration","type":"Class"},{"name":"IInformaticsGatewayClient","href":"Monai.Deploy.InformaticsGateway.Client.IInformaticsGatewayClient.html","topicHref":"Monai.Deploy.InformaticsGateway.Client.IInformaticsGatewayClient.html","topicUid":"Monai.Deploy.InformaticsGateway.Client.IInformaticsGatewayClient","type":"Interface"},{"name":"InformaticsGatewayClient","href":"Monai.Deploy.InformaticsGateway.Client.InformaticsGatewayClient.html","topicHref":"Monai.Deploy.InformaticsGateway.Client.InformaticsGatewayClient.html","topicUid":"Monai.Deploy.InformaticsGateway.Client.InformaticsGatewayClient","type":"Class"},{"name":"Log","href":"Monai.Deploy.InformaticsGateway.Client.Log.html","topicHref":"Monai.Deploy.InformaticsGateway.Client.Log.html","topicUid":"Monai.Deploy.InformaticsGateway.Client.Log","type":"Class"}]},{"name":"Monai.Deploy.InformaticsGateway.Client.Common","href":"Monai.Deploy.InformaticsGateway.Client.Common.html","topicHref":"Monai.Deploy.InformaticsGateway.Client.Common.html","topicUid":"Monai.Deploy.InformaticsGateway.Client.Common","type":"Namespace","items":[{"name":"GuardExtensions","href":"Monai.Deploy.InformaticsGateway.Client.Common.GuardExtensions.html","topicHref":"Monai.Deploy.InformaticsGateway.Client.Common.GuardExtensions.html","topicUid":"Monai.Deploy.InformaticsGateway.Client.Common.GuardExtensions","type":"Class"},{"name":"ProblemDetails","href":"Monai.Deploy.InformaticsGateway.Client.Common.ProblemDetails.html","topicHref":"Monai.Deploy.InformaticsGateway.Client.Common.ProblemDetails.html","topicUid":"Monai.Deploy.InformaticsGateway.Client.Common.ProblemDetails","type":"Class"},{"name":"ProblemException","href":"Monai.Deploy.InformaticsGateway.Client.Common.ProblemException.html","topicHref":"Monai.Deploy.InformaticsGateway.Client.Common.ProblemException.html","topicUid":"Monai.Deploy.InformaticsGateway.Client.Common.ProblemException","type":"Class"},{"name":"UriExtensions","href":"Monai.Deploy.InformaticsGateway.Client.Common.UriExtensions.html","topicHref":"Monai.Deploy.InformaticsGateway.Client.Common.UriExtensions.html","topicUid":"Monai.Deploy.InformaticsGateway.Client.Common.UriExtensions","type":"Class"}]},{"name":"Monai.Deploy.InformaticsGateway.Client.Services","href":"Monai.Deploy.InformaticsGateway.Client.Services.html","topicHref":"Monai.Deploy.InformaticsGateway.Client.Services.html","topicUid":"Monai.Deploy.InformaticsGateway.Client.Services","type":"Namespace","items":[{"name":"IAeTitleService<T>","href":"Monai.Deploy.InformaticsGateway.Client.Services.IAeTitleService-1.html","topicHref":"Monai.Deploy.InformaticsGateway.Client.Services.IAeTitleService-1.html","topicUid":"Monai.Deploy.InformaticsGateway.Client.Services.IAeTitleService`1","type":"Interface"},{"name":"IHealthService","href":"Monai.Deploy.InformaticsGateway.Client.Services.IHealthService.html","topicHref":"Monai.Deploy.InformaticsGateway.Client.Services.IHealthService.html","topicUid":"Monai.Deploy.InformaticsGateway.Client.Services.IHealthService","type":"Interface"},{"name":"IInferenceService","href":"Monai.Deploy.InformaticsGateway.Client.Services.IInferenceService.html","topicHref":"Monai.Deploy.InformaticsGateway.Client.Services.IInferenceService.html","topicUid":"Monai.Deploy.InformaticsGateway.Client.Services.IInferenceService","type":"Interface"}]},{"name":"Monai.Deploy.InformaticsGateway.Common","href":"Monai.Deploy.InformaticsGateway.Common.html","topicHref":"Monai.Deploy.InformaticsGateway.Common.html","topicUid":"Monai.Deploy.InformaticsGateway.Common","type":"Namespace","items":[{"name":"ExtensionMethods","href":"Monai.Deploy.InformaticsGateway.Common.ExtensionMethods.html","topicHref":"Monai.Deploy.InformaticsGateway.Common.ExtensionMethods.html","topicUid":"Monai.Deploy.InformaticsGateway.Common.ExtensionMethods","type":"Class"},{"name":"FileSystemExtensions","href":"Monai.Deploy.InformaticsGateway.Common.FileSystemExtensions.html","topicHref":"Monai.Deploy.InformaticsGateway.Common.FileSystemExtensions.html","topicUid":"Monai.Deploy.InformaticsGateway.Common.FileSystemExtensions","type":"Class"}]},{"name":"Monai.Deploy.InformaticsGateway.Configuration","href":"Monai.Deploy.InformaticsGateway.Configuration.html","topicHref":"Monai.Deploy.InformaticsGateway.Configuration.html","topicUid":"Monai.Deploy.InformaticsGateway.Configuration","type":"Namespace","items":[{"name":"ConfigurationException","href":"Monai.Deploy.InformaticsGateway.Configuration.ConfigurationException.html","topicHref":"Monai.Deploy.InformaticsGateway.Configuration.ConfigurationException.html","topicUid":"Monai.Deploy.InformaticsGateway.Configuration.ConfigurationException","type":"Class"},{"name":"ConfigurationValidator","href":"Monai.Deploy.InformaticsGateway.Configuration.ConfigurationValidator.html","topicHref":"Monai.Deploy.InformaticsGateway.Configuration.ConfigurationValidator.html","topicUid":"Monai.Deploy.InformaticsGateway.Configuration.ConfigurationValidator","type":"Class"},{"name":"DataExportConfiguration","href":"Monai.Deploy.InformaticsGateway.Configuration.DataExportConfiguration.html","topicHref":"Monai.Deploy.InformaticsGateway.Configuration.DataExportConfiguration.html","topicUid":"Monai.Deploy.InformaticsGateway.Configuration.DataExportConfiguration","type":"Class"},{"name":"DatabaseOptions","href":"Monai.Deploy.InformaticsGateway.Configuration.DatabaseOptions.html","topicHref":"Monai.Deploy.InformaticsGateway.Configuration.DatabaseOptions.html","topicUid":"Monai.Deploy.InformaticsGateway.Configuration.DatabaseOptions","type":"Class"},{"name":"DicomConfiguration","href":"Monai.Deploy.InformaticsGateway.Configuration.DicomConfiguration.html","topicHref":"Monai.Deploy.InformaticsGateway.Configuration.DicomConfiguration.html","topicUid":"Monai.Deploy.InformaticsGateway.Configuration.DicomConfiguration","type":"Class"},{"name":"DicomJsonOptions","href":"Monai.Deploy.InformaticsGateway.Configuration.DicomJsonOptions.html","topicHref":"Monai.Deploy.InformaticsGateway.Configuration.DicomJsonOptions.html","topicUid":"Monai.Deploy.InformaticsGateway.Configuration.DicomJsonOptions","type":"Enum"},{"name":"DicomWebConfiguration","href":"Monai.Deploy.InformaticsGateway.Configuration.DicomWebConfiguration.html","topicHref":"Monai.Deploy.InformaticsGateway.Configuration.DicomWebConfiguration.html","topicUid":"Monai.Deploy.InformaticsGateway.Configuration.DicomWebConfiguration","type":"Class"},{"name":"FhirConfiguration","href":"Monai.Deploy.InformaticsGateway.Configuration.FhirConfiguration.html","topicHref":"Monai.Deploy.InformaticsGateway.Configuration.FhirConfiguration.html","topicUid":"Monai.Deploy.InformaticsGateway.Configuration.FhirConfiguration","type":"Class"},{"name":"Hl7Configuration","href":"Monai.Deploy.InformaticsGateway.Configuration.Hl7Configuration.html","topicHref":"Monai.Deploy.InformaticsGateway.Configuration.Hl7Configuration.html","topicUid":"Monai.Deploy.InformaticsGateway.Configuration.Hl7Configuration","type":"Class"},{"name":"HttpEndpointSettings","href":"Monai.Deploy.InformaticsGateway.Configuration.HttpEndpointSettings.html","topicHref":"Monai.Deploy.InformaticsGateway.Configuration.HttpEndpointSettings.html","topicUid":"Monai.Deploy.InformaticsGateway.Configuration.HttpEndpointSettings","type":"Class"},{"name":"InformaticsGatewayConfiguration","href":"Monai.Deploy.InformaticsGateway.Configuration.InformaticsGatewayConfiguration.html","topicHref":"Monai.Deploy.InformaticsGateway.Configuration.InformaticsGatewayConfiguration.html","topicUid":"Monai.Deploy.InformaticsGateway.Configuration.InformaticsGatewayConfiguration","type":"Class"},{"name":"MessageBrokerConfiguration","href":"Monai.Deploy.InformaticsGateway.Configuration.MessageBrokerConfiguration.html","topicHref":"Monai.Deploy.InformaticsGateway.Configuration.MessageBrokerConfiguration.html","topicUid":"Monai.Deploy.InformaticsGateway.Configuration.MessageBrokerConfiguration","type":"Class"},{"name":"MessageBrokerConfigurationKeys","href":"Monai.Deploy.InformaticsGateway.Configuration.MessageBrokerConfigurationKeys.html","topicHref":"Monai.Deploy.InformaticsGateway.Configuration.MessageBrokerConfigurationKeys.html","topicUid":"Monai.Deploy.InformaticsGateway.Configuration.MessageBrokerConfigurationKeys","type":"Class"},{"name":"PlugInConfiguration","href":"Monai.Deploy.InformaticsGateway.Configuration.PlugInConfiguration.html","topicHref":"Monai.Deploy.InformaticsGateway.Configuration.PlugInConfiguration.html","topicUid":"Monai.Deploy.InformaticsGateway.Configuration.PlugInConfiguration","type":"Class"},{"name":"RetryConfiguration","href":"Monai.Deploy.InformaticsGateway.Configuration.RetryConfiguration.html","topicHref":"Monai.Deploy.InformaticsGateway.Configuration.RetryConfiguration.html","topicUid":"Monai.Deploy.InformaticsGateway.Configuration.RetryConfiguration","type":"Class"},{"name":"ScpConfiguration","href":"Monai.Deploy.InformaticsGateway.Configuration.ScpConfiguration.html","topicHref":"Monai.Deploy.InformaticsGateway.Configuration.ScpConfiguration.html","topicUid":"Monai.Deploy.InformaticsGateway.Configuration.ScpConfiguration","type":"Class"},{"name":"ScuConfiguration","href":"Monai.Deploy.InformaticsGateway.Configuration.ScuConfiguration.html","topicHref":"Monai.Deploy.InformaticsGateway.Configuration.ScuConfiguration.html","topicUid":"Monai.Deploy.InformaticsGateway.Configuration.ScuConfiguration","type":"Class"},{"name":"StorageConfiguration","href":"Monai.Deploy.InformaticsGateway.Configuration.StorageConfiguration.html","topicHref":"Monai.Deploy.InformaticsGateway.Configuration.StorageConfiguration.html","topicUid":"Monai.Deploy.InformaticsGateway.Configuration.StorageConfiguration","type":"Class"},{"name":"TemporaryDataStorageLocation","href":"Monai.Deploy.InformaticsGateway.Configuration.TemporaryDataStorageLocation.html","topicHref":"Monai.Deploy.InformaticsGateway.Configuration.TemporaryDataStorageLocation.html","topicUid":"Monai.Deploy.InformaticsGateway.Configuration.TemporaryDataStorageLocation","type":"Enum"},{"name":"ValidationExtensions","href":"Monai.Deploy.InformaticsGateway.Configuration.ValidationExtensions.html","topicHref":"Monai.Deploy.InformaticsGateway.Configuration.ValidationExtensions.html","topicUid":"Monai.Deploy.InformaticsGateway.Configuration.ValidationExtensions","type":"Class"}]},{"name":"Monai.Deploy.InformaticsGateway.Database","href":"Monai.Deploy.InformaticsGateway.Database.html","topicHref":"Monai.Deploy.InformaticsGateway.Database.html","topicUid":"Monai.Deploy.InformaticsGateway.Database","type":"Namespace","items":[{"name":"DatabaseManager","href":"Monai.Deploy.InformaticsGateway.Database.DatabaseManager.html","topicHref":"Monai.Deploy.InformaticsGateway.Database.DatabaseManager.html","topicUid":"Monai.Deploy.InformaticsGateway.Database.DatabaseManager","type":"Class"},{"name":"DatabaseMigrationManager","href":"Monai.Deploy.InformaticsGateway.Database.DatabaseMigrationManager.html","topicHref":"Monai.Deploy.InformaticsGateway.Database.DatabaseMigrationManager.html","topicUid":"Monai.Deploy.InformaticsGateway.Database.DatabaseMigrationManager","type":"Class"}]},{"name":"Monai.Deploy.InformaticsGateway.Database.Api","href":"Monai.Deploy.InformaticsGateway.Database.Api.html","topicHref":"Monai.Deploy.InformaticsGateway.Database.Api.html","topicUid":"Monai.Deploy.InformaticsGateway.Database.Api","type":"Namespace","items":[{"name":"DatabaseException","href":"Monai.Deploy.InformaticsGateway.Database.Api.DatabaseException.html","topicHref":"Monai.Deploy.InformaticsGateway.Database.Api.DatabaseException.html","topicUid":"Monai.Deploy.InformaticsGateway.Database.Api.DatabaseException","type":"Class"},{"name":"DatabaseRegistrationBase","href":"Monai.Deploy.InformaticsGateway.Database.Api.DatabaseRegistrationBase.html","topicHref":"Monai.Deploy.InformaticsGateway.Database.Api.DatabaseRegistrationBase.html","topicUid":"Monai.Deploy.InformaticsGateway.Database.Api.DatabaseRegistrationBase","type":"Class"},{"name":"DatabaseType","href":"Monai.Deploy.InformaticsGateway.Database.Api.DatabaseType.html","topicHref":"Monai.Deploy.InformaticsGateway.Database.Api.DatabaseType.html","topicUid":"Monai.Deploy.InformaticsGateway.Database.Api.DatabaseType","type":"Enum"},{"name":"IDatabaseMigrationManager","href":"Monai.Deploy.InformaticsGateway.Database.Api.IDatabaseMigrationManager.html","topicHref":"Monai.Deploy.InformaticsGateway.Database.Api.IDatabaseMigrationManager.html","topicUid":"Monai.Deploy.InformaticsGateway.Database.Api.IDatabaseMigrationManager","type":"Interface"},{"name":"IDatabaseMigrationManagerForPlugIns","href":"Monai.Deploy.InformaticsGateway.Database.Api.IDatabaseMigrationManagerForPlugIns.html","topicHref":"Monai.Deploy.InformaticsGateway.Database.Api.IDatabaseMigrationManagerForPlugIns.html","topicUid":"Monai.Deploy.InformaticsGateway.Database.Api.IDatabaseMigrationManagerForPlugIns","type":"Interface"},{"name":"SR","href":"Monai.Deploy.InformaticsGateway.Database.Api.SR.html","topicHref":"Monai.Deploy.InformaticsGateway.Database.Api.SR.html","topicUid":"Monai.Deploy.InformaticsGateway.Database.Api.SR","type":"Class"},{"name":"StorageMetadataWrapper","href":"Monai.Deploy.InformaticsGateway.Database.Api.StorageMetadataWrapper.html","topicHref":"Monai.Deploy.InformaticsGateway.Database.Api.StorageMetadataWrapper.html","topicUid":"Monai.Deploy.InformaticsGateway.Database.Api.StorageMetadataWrapper","type":"Class"}]},{"name":"Monai.Deploy.InformaticsGateway.Database.Api.Logging","href":"Monai.Deploy.InformaticsGateway.Database.Api.Logging.html","topicHref":"Monai.Deploy.InformaticsGateway.Database.Api.Logging.html","topicUid":"Monai.Deploy.InformaticsGateway.Database.Api.Logging","type":"Namespace","items":[{"name":"Log","href":"Monai.Deploy.InformaticsGateway.Database.Api.Logging.Log.html","topicHref":"Monai.Deploy.InformaticsGateway.Database.Api.Logging.Log.html","topicUid":"Monai.Deploy.InformaticsGateway.Database.Api.Logging.Log","type":"Class"}]},{"name":"Monai.Deploy.InformaticsGateway.Database.Api.Repositories","href":"Monai.Deploy.InformaticsGateway.Database.Api.Repositories.html","topicHref":"Monai.Deploy.InformaticsGateway.Database.Api.Repositories.html","topicUid":"Monai.Deploy.InformaticsGateway.Database.Api.Repositories","type":"Namespace","items":[{"name":"IDestinationApplicationEntityRepository","href":"Monai.Deploy.InformaticsGateway.Database.Api.Repositories.IDestinationApplicationEntityRepository.html","topicHref":"Monai.Deploy.InformaticsGateway.Database.Api.Repositories.IDestinationApplicationEntityRepository.html","topicUid":"Monai.Deploy.InformaticsGateway.Database.Api.Repositories.IDestinationApplicationEntityRepository","type":"Interface"},{"name":"IDicomAssociationInfoRepository","href":"Monai.Deploy.InformaticsGateway.Database.Api.Repositories.IDicomAssociationInfoRepository.html","topicHref":"Monai.Deploy.InformaticsGateway.Database.Api.Repositories.IDicomAssociationInfoRepository.html","topicUid":"Monai.Deploy.InformaticsGateway.Database.Api.Repositories.IDicomAssociationInfoRepository","type":"Interface"},{"name":"IExternalAppDetailsRepository","href":"Monai.Deploy.InformaticsGateway.Database.Api.Repositories.IExternalAppDetailsRepository.html","topicHref":"Monai.Deploy.InformaticsGateway.Database.Api.Repositories.IExternalAppDetailsRepository.html","topicUid":"Monai.Deploy.InformaticsGateway.Database.Api.Repositories.IExternalAppDetailsRepository","type":"Interface"},{"name":"IHL7DestinationEntityRepository","href":"Monai.Deploy.InformaticsGateway.Database.Api.Repositories.IHL7DestinationEntityRepository.html","topicHref":"Monai.Deploy.InformaticsGateway.Database.Api.Repositories.IHL7DestinationEntityRepository.html","topicUid":"Monai.Deploy.InformaticsGateway.Database.Api.Repositories.IHL7DestinationEntityRepository","type":"Interface"},{"name":"IHl7ApplicationConfigRepository","href":"Monai.Deploy.InformaticsGateway.Database.Api.Repositories.IHl7ApplicationConfigRepository.html","topicHref":"Monai.Deploy.InformaticsGateway.Database.Api.Repositories.IHl7ApplicationConfigRepository.html","topicUid":"Monai.Deploy.InformaticsGateway.Database.Api.Repositories.IHl7ApplicationConfigRepository","type":"Interface"},{"name":"IInferenceRequestRepository","href":"Monai.Deploy.InformaticsGateway.Database.Api.Repositories.IInferenceRequestRepository.html","topicHref":"Monai.Deploy.InformaticsGateway.Database.Api.Repositories.IInferenceRequestRepository.html","topicUid":"Monai.Deploy.InformaticsGateway.Database.Api.Repositories.IInferenceRequestRepository","type":"Interface"},{"name":"IMonaiApplicationEntityRepository","href":"Monai.Deploy.InformaticsGateway.Database.Api.Repositories.IMonaiApplicationEntityRepository.html","topicHref":"Monai.Deploy.InformaticsGateway.Database.Api.Repositories.IMonaiApplicationEntityRepository.html","topicUid":"Monai.Deploy.InformaticsGateway.Database.Api.Repositories.IMonaiApplicationEntityRepository","type":"Interface"},{"name":"IPayloadRepository","href":"Monai.Deploy.InformaticsGateway.Database.Api.Repositories.IPayloadRepository.html","topicHref":"Monai.Deploy.InformaticsGateway.Database.Api.Repositories.IPayloadRepository.html","topicUid":"Monai.Deploy.InformaticsGateway.Database.Api.Repositories.IPayloadRepository","type":"Interface"},{"name":"ISourceApplicationEntityRepository","href":"Monai.Deploy.InformaticsGateway.Database.Api.Repositories.ISourceApplicationEntityRepository.html","topicHref":"Monai.Deploy.InformaticsGateway.Database.Api.Repositories.ISourceApplicationEntityRepository.html","topicUid":"Monai.Deploy.InformaticsGateway.Database.Api.Repositories.ISourceApplicationEntityRepository","type":"Interface"},{"name":"IStorageMetadataRepository","href":"Monai.Deploy.InformaticsGateway.Database.Api.Repositories.IStorageMetadataRepository.html","topicHref":"Monai.Deploy.InformaticsGateway.Database.Api.Repositories.IStorageMetadataRepository.html","topicUid":"Monai.Deploy.InformaticsGateway.Database.Api.Repositories.IStorageMetadataRepository","type":"Interface"},{"name":"IVirtualApplicationEntityRepository","href":"Monai.Deploy.InformaticsGateway.Database.Api.Repositories.IVirtualApplicationEntityRepository.html","topicHref":"Monai.Deploy.InformaticsGateway.Database.Api.Repositories.IVirtualApplicationEntityRepository.html","topicUid":"Monai.Deploy.InformaticsGateway.Database.Api.Repositories.IVirtualApplicationEntityRepository","type":"Interface"},{"name":"InferenceRequestRepositoryBase","href":"Monai.Deploy.InformaticsGateway.Database.Api.Repositories.InferenceRequestRepositoryBase.html","topicHref":"Monai.Deploy.InformaticsGateway.Database.Api.Repositories.InferenceRequestRepositoryBase.html","topicUid":"Monai.Deploy.InformaticsGateway.Database.Api.Repositories.InferenceRequestRepositoryBase","type":"Class"},{"name":"StorageMetadataRepositoryBase","href":"Monai.Deploy.InformaticsGateway.Database.Api.Repositories.StorageMetadataRepositoryBase.html","topicHref":"Monai.Deploy.InformaticsGateway.Database.Api.Repositories.StorageMetadataRepositoryBase.html","topicUid":"Monai.Deploy.InformaticsGateway.Database.Api.Repositories.StorageMetadataRepositoryBase","type":"Class"}]},{"name":"Monai.Deploy.InformaticsGateway.DicomWeb.Client","href":"Monai.Deploy.InformaticsGateway.DicomWeb.Client.html","topicHref":"Monai.Deploy.InformaticsGateway.DicomWeb.Client.html","topicUid":"Monai.Deploy.InformaticsGateway.DicomWeb.Client","type":"Namespace","items":[{"name":"DicomWebClient","href":"Monai.Deploy.InformaticsGateway.DicomWeb.Client.DicomWebClient.html","topicHref":"Monai.Deploy.InformaticsGateway.DicomWeb.Client.DicomWebClient.html","topicUid":"Monai.Deploy.InformaticsGateway.DicomWeb.Client.DicomWebClient","type":"Class"}]},{"name":"Monai.Deploy.InformaticsGateway.DicomWeb.Client.API","href":"Monai.Deploy.InformaticsGateway.DicomWeb.Client.API.html","topicHref":"Monai.Deploy.InformaticsGateway.DicomWeb.Client.API.html","topicUid":"Monai.Deploy.InformaticsGateway.DicomWeb.Client.API","type":"Namespace","items":[{"name":"DicomWebClientException","href":"Monai.Deploy.InformaticsGateway.DicomWeb.Client.API.DicomWebClientException.html","topicHref":"Monai.Deploy.InformaticsGateway.DicomWeb.Client.API.DicomWebClientException.html","topicUid":"Monai.Deploy.InformaticsGateway.DicomWeb.Client.API.DicomWebClientException","type":"Class"},{"name":"DicomWebResponse<T>","href":"Monai.Deploy.InformaticsGateway.DicomWeb.Client.API.DicomWebResponse-1.html","topicHref":"Monai.Deploy.InformaticsGateway.DicomWeb.Client.API.DicomWebResponse-1.html","topicUid":"Monai.Deploy.InformaticsGateway.DicomWeb.Client.API.DicomWebResponse`1","type":"Class"},{"name":"DicomWebServiceType","href":"Monai.Deploy.InformaticsGateway.DicomWeb.Client.API.DicomWebServiceType.html","topicHref":"Monai.Deploy.InformaticsGateway.DicomWeb.Client.API.DicomWebServiceType.html","topicUid":"Monai.Deploy.InformaticsGateway.DicomWeb.Client.API.DicomWebServiceType","type":"Enum"},{"name":"IDicomWebClient","href":"Monai.Deploy.InformaticsGateway.DicomWeb.Client.API.IDicomWebClient.html","topicHref":"Monai.Deploy.InformaticsGateway.DicomWeb.Client.API.IDicomWebClient.html","topicUid":"Monai.Deploy.InformaticsGateway.DicomWeb.Client.API.IDicomWebClient","type":"Interface"},{"name":"IQidoService","href":"Monai.Deploy.InformaticsGateway.DicomWeb.Client.API.IQidoService.html","topicHref":"Monai.Deploy.InformaticsGateway.DicomWeb.Client.API.IQidoService.html","topicUid":"Monai.Deploy.InformaticsGateway.DicomWeb.Client.API.IQidoService","type":"Interface"},{"name":"IServiceBase","href":"Monai.Deploy.InformaticsGateway.DicomWeb.Client.API.IServiceBase.html","topicHref":"Monai.Deploy.InformaticsGateway.DicomWeb.Client.API.IServiceBase.html","topicUid":"Monai.Deploy.InformaticsGateway.DicomWeb.Client.API.IServiceBase","type":"Interface"},{"name":"IStowService","href":"Monai.Deploy.InformaticsGateway.DicomWeb.Client.API.IStowService.html","topicHref":"Monai.Deploy.InformaticsGateway.DicomWeb.Client.API.IStowService.html","topicUid":"Monai.Deploy.InformaticsGateway.DicomWeb.Client.API.IStowService","type":"Interface"},{"name":"IWadoService","href":"Monai.Deploy.InformaticsGateway.DicomWeb.Client.API.IWadoService.html","topicHref":"Monai.Deploy.InformaticsGateway.DicomWeb.Client.API.IWadoService.html","topicUid":"Monai.Deploy.InformaticsGateway.DicomWeb.Client.API.IWadoService","type":"Interface"},{"name":"MimeMappings","href":"Monai.Deploy.InformaticsGateway.DicomWeb.Client.API.MimeMappings.html","topicHref":"Monai.Deploy.InformaticsGateway.DicomWeb.Client.API.MimeMappings.html","topicUid":"Monai.Deploy.InformaticsGateway.DicomWeb.Client.API.MimeMappings","type":"Class"},{"name":"MimeType","href":"Monai.Deploy.InformaticsGateway.DicomWeb.Client.API.MimeType.html","topicHref":"Monai.Deploy.InformaticsGateway.DicomWeb.Client.API.MimeType.html","topicUid":"Monai.Deploy.InformaticsGateway.DicomWeb.Client.API.MimeType","type":"Enum"},{"name":"ResponseDecodeException","href":"Monai.Deploy.InformaticsGateway.DicomWeb.Client.API.ResponseDecodeException.html","topicHref":"Monai.Deploy.InformaticsGateway.DicomWeb.Client.API.ResponseDecodeException.html","topicUid":"Monai.Deploy.InformaticsGateway.DicomWeb.Client.API.ResponseDecodeException","type":"Class"},{"name":"UnsupportedReturnTypeException","href":"Monai.Deploy.InformaticsGateway.DicomWeb.Client.API.UnsupportedReturnTypeException.html","topicHref":"Monai.Deploy.InformaticsGateway.DicomWeb.Client.API.UnsupportedReturnTypeException.html","topicUid":"Monai.Deploy.InformaticsGateway.DicomWeb.Client.API.UnsupportedReturnTypeException","type":"Class"}]},{"name":"Monai.Deploy.InformaticsGateway.DicomWeb.Client.Common","href":"Monai.Deploy.InformaticsGateway.DicomWeb.Client.Common.html","topicHref":"Monai.Deploy.InformaticsGateway.DicomWeb.Client.Common.html","topicUid":"Monai.Deploy.InformaticsGateway.DicomWeb.Client.Common","type":"Namespace","items":[{"name":"Extensions","href":"Monai.Deploy.InformaticsGateway.DicomWeb.Client.Common.Extensions.html","topicHref":"Monai.Deploy.InformaticsGateway.DicomWeb.Client.Common.Extensions.html","topicUid":"Monai.Deploy.InformaticsGateway.DicomWeb.Client.Common.Extensions","type":"Class"}]},{"name":"System.Net.Http","href":"System.Net.Http.html","topicHref":"System.Net.Http.html","topicUid":"System.Net.Http","type":"Namespace","items":[{"name":"MultipartMemoryStreamProvider","href":"System.Net.Http.MultipartMemoryStreamProvider.html","topicHref":"System.Net.Http.MultipartMemoryStreamProvider.html","topicUid":"System.Net.Http.MultipartMemoryStreamProvider","type":"Class"},{"name":"MultipartStreamProvider","href":"System.Net.Http.MultipartStreamProvider.html","topicHref":"System.Net.Http.MultipartStreamProvider.html","topicUid":"System.Net.Http.MultipartStreamProvider","type":"Class"}]}],"memberLayout":"SamePage"}
